podcast_creator/__init__.py
podcast_creator/cli.py
podcast_creator/config.py
podcast_creator/core.py
podcast_creator/episodes.py
podcast_creator/graph.py
podcast_creator/nodes.py
podcast_creator/speakers.py
podcast_creator/state.py
podcast_creator/validators.py
podcast_creator/resources/episodes_config.json
podcast_creator/resources/speakers_config.json
podcast_creator/resources/examples/example_usage.py
podcast_creator/resources/prompts/podcast/outline.jinja
podcast_creator/resources/prompts/podcast/transcript.jinja
podcast_creator/resources/streamlit_app/README.md
podcast_creator/resources/streamlit_app/app.py
podcast_creator/resources/streamlit_app/utils/__init__.py
podcast_creator/resources/streamlit_app/utils/async_helpers.py
podcast_creator/resources/streamlit_app/utils/content_extractor.py
podcast_creator/resources/streamlit_app/utils/episode_manager.py
podcast_creator/resources/streamlit_app/utils/error_handler.py
podcast_creator/resources/streamlit_app/utils/profile_manager.py
podcast_creator/resources/streamlit_app/utils/provider_checker.py
podcast_creator/resources/streamlit_app/utils/voice_provider.py
podcast_creator-0.9.0.dist-info/METADATA
podcast_creator-0.9.0.dist-info/WHEEL
podcast_creator-0.9.0.dist-info/entry_points.txt
podcast_creator-0.9.0.dist-info/licenses/LICENSE
podcast_creator-0.9.0.dist-info/RECORD
