Metadata-Version: 2.4
Name: podcast-creator
Version: 0.9.0
Summary: AI-powered podcast generation tool that creates conversational audio content from text sources
License-Expression: MIT
License-File: LICENSE
Requires-Python: >=3.10.6
Requires-Dist: ai-prompter>=0.3.1
Requires-Dist: click>=8.0.0
Requires-Dist: content-core>=1.14.1
Requires-Dist: esperanto>=2.18.0
Requires-Dist: langgraph>=1.0.6
Requires-Dist: loguru>=0.7.3
Requires-Dist: moviepy>=2.2.1
Requires-Dist: nest-asyncio>=1.6.0
Requires-Dist: pydub>=0.25.1
Requires-Dist: python-dotenv>=1.1.1
Requires-Dist: requests>=2.0
Requires-Dist: tiktoken>=0.9.0
Provides-Extra: ui
Requires-Dist: streamlit>=1.46.1; extra == 'ui'
